novel_kit_cli/__init__.py
novel_kit_cli-0.0.4.dist-info/METADATA
novel_kit_cli-0.0.4.dist-info/WHEEL
novel_kit_cli-0.0.4.dist-info/entry_points.txt
novel_kit_cli-0.0.4.dist-info/RECORD
