Metadata-Version: 2.4
Name: novel-kit-cli
Version: 0.0.4
Summary: NovelKit CLI - AI-Assisted Novel Writing Toolkit
Requires-Python: >=3.11
Requires-Dist: httpx>=0.24.0
Requires-Dist: readchar>=3.0.0
Requires-Dist: rich>=13.0.0
Requires-Dist: typer>=0.9.0
